{"id":"form-based-authentication;using-username-and-password-to-log-in","name":"Using username and password to log in","title":"Using username and password to log in","manual":false,"testSteps":[{"number":1,"description":"Using username and password to log in #1 - username: tomsmith, password: SuperSecretPassword!, outcome: succeeded","startTime":1666015653963,"children":[{"number":2,"description":"Given Alice starts with the \"Form Authentication\" example","startTime":1666015653966,"children":[{"number":3,"description":"Alice navigates to '/'","startTime":1666015653997,"children":[],"reportData":[],"screenshots":[{"screenshot":"photo-linux-chromium-106.0.5249.30-alice-navigates-to-ff5c157a7a.png","timeStamp":1666015654778}],"duration":659,"result":"SUCCESS"},{"number":4,"description":"Alice picks example called Form Authentication","startTime":1666015654788,"children":[{"number":5,"description":"Alice clicks on the first of available examples where Text does equal 'Form Authentication'","startTime":1666015654798,"children":[],"reportData":[],"screenshots":[{"screenshot":"photo-linux-chromium-106.0.5249.30-alice-clicks-on-the-first-of-availa-0176bd8057.png","timeStamp":1666015655444}],"duration":519,"result":"SUCCESS"}],"reportData":[],"screenshots":[],"duration":530,"result":"SUCCESS"}],"reportData":[],"screenshots":[],"duration":1353,"result":"SUCCESS"},{"number":6,"description":"When she logs in using \"tomsmith\" and \"SuperSecretPassword!\"","startTime":1666015655321,"children":[{"number":7,"description":"Alice logs in as tomsmith","startTime":1666015655451,"children":[{"number":8,"description":"Alice enters 'tomsmith' into username field","startTime":1666015655462,"children":[],"reportData":[],"screenshots":[{"screenshot":"photo-linux-chromium-106.0.5249.30-alice-enters-tomsmith-into-userna-6f2e6ef841.png","timeStamp":1666015655594}],"duration":32,"result":"SUCCESS"},{"number":9,"description":"Alice enters 'SuperSecretPassword!' into password field","startTime":1666015655596,"children":[],"reportData":[],"screenshots":[{"screenshot":"photo-linux-chromium-106.0.5249.30-alice-enters-supersecretpassword-c1d8af910b.png","timeStamp":1666015655730}],"duration":23,"result":"SUCCESS"},{"number":10,"description":"Alice clicks on login button","startTime":1666015655741,"children":[],"reportData":[],"screenshots":[{"screenshot":"photo-linux-chromium-106.0.5249.30-alice-clicks-on-login-button-8a8fc86c12.png","timeStamp":1666015656090}],"duration":210,"result":"SUCCESS"}],"reportData":[],"screenshots":[],"duration":501,"result":"SUCCESS"}],"reportData":[],"screenshots":[],"duration":632,"result":"SUCCESS"},{"number":11,"description":"Then she should see that authentication has succeeded","startTime":1666015655953,"children":[{"number":12,"description":"Alice verifies that authentication has succeeded","startTime":1666015656093,"children":[{"number":13,"description":"Alice verifies that flash alert is present","startTime":1666015656104,"children":[{"number":14,"description":"Alice ensures that flash message does become visible","startTime":1666015656114,"children":[],"reportData":[],"screenshots":[{"screenshot":"photo-linux-chromium-106.0.5249.30-alice-ensures-that-flash-message-do-9ac7ff61db.png","timeStamp":1666015656256}],"duration":38,"result":"SUCCESS"}],"reportData":[],"screenshots":[],"duration":49,"result":"SUCCESS"},{"number":15,"description":"Alice ensures that the text of flash message does include 'You logged into a secure area!'","startTime":1666015656265,"children":[],"reportData":[],"screenshots":[{"screenshot":"photo-linux-chromium-106.0.5249.30-alice-ensures-that-the-text-of-flas-9ac7ff61db.png","timeStamp":1666015656371}],"duration":11,"result":"SUCCESS"}],"reportData":[],"screenshots":[],"duration":184,"result":"SUCCESS"}],"reportData":[],"screenshots":[],"duration":325,"result":"SUCCESS"}],"reportData":[],"screenshots":[],"duration":2429,"result":"SUCCESS"},{"number":16,"description":"Using username and password to log in #2 - username: foobar, password: barfoo, outcome: failed","startTime":1666015656400,"children":[{"number":17,"description":"Given Alice starts with the \"Form Authentication\" example","startTime":1666015656401,"children":[{"number":18,"description":"Alice navigates to '/'","startTime":1666015656418,"children":[],"reportData":[],"screenshots":[{"screenshot":"photo-linux-chromium-106.0.5249.30-alice-navigates-to-ff5c157a7a.png","timeStamp":1666015657105}],"duration":584,"result":"SUCCESS"},{"number":19,"description":"Alice picks example called Form Authentication","startTime":1666015657115,"children":[{"number":20,"description":"Alice clicks on the first of available examples where Text does equal 'Form Authentication'","startTime":1666015657125,"children":[],"reportData":[],"screenshots":[{"screenshot":"photo-linux-chromium-106.0.5249.30-alice-clicks-on-the-first-of-availa-15e4260f84.png","timeStamp":1666015657676}],"duration":430,"result":"SUCCESS"}],"reportData":[],"screenshots":[],"duration":441,"result":"SUCCESS"}],"reportData":[],"screenshots":[],"duration":1156,"result":"SUCCESS"},{"number":21,"description":"When she logs in using \"foobar\" and \"barfoo\"","startTime":1666015657557,"children":[{"number":22,"description":"Alice logs in as foobar","startTime":1666015657684,"children":[{"number":23,"description":"Alice enters 'foobar' into username field","startTime":1666015657694,"children":[],"reportData":[],"screenshots":[{"screenshot":"photo-linux-chromium-106.0.5249.30-alice-enters-foobar-into-username-e570514795.png","timeStamp":1666015657841}],"duration":41,"result":"SUCCESS"},{"number":24,"description":"Alice enters 'barfoo' into password field","startTime":1666015657851,"children":[],"reportData":[],"screenshots":[{"screenshot":"photo-linux-chromium-106.0.5249.30-alice-enters-barfoo-into-password-ed05d2a941.png","timeStamp":1666015657973}],"duration":22,"result":"SUCCESS"},{"number":25,"description":"Alice clicks on login button","startTime":1666015657977,"children":[],"reportData":[],"screenshots":[{"screenshot":"photo-linux-chromium-106.0.5249.30-alice-clicks-on-login-button-46b7eff829.png","timeStamp":1666015658340}],"duration":218,"result":"SUCCESS"}],"reportData":[],"screenshots":[],"duration":511,"result":"SUCCESS"}],"reportData":[],"screenshots":[],"duration":639,"result":"SUCCESS"},{"number":26,"description":"Then she should see that authentication has failed","startTime":1666015658196,"children":[{"number":27,"description":"Alice verifies that authentication has failed","startTime":1666015658346,"children":[{"number":28,"description":"Alice verifies that flash alert is present","startTime":1666015658356,"children":[{"number":29,"description":"Alice ensures that flash message does become visible","startTime":1666015658366,"children":[],"reportData":[],"screenshots":[{"screenshot":"photo-linux-chromium-106.0.5249.30-alice-ensures-that-flash-message-do-55b4a6be71.png","timeStamp":1666015658510}],"duration":36,"result":"SUCCESS"}],"reportData":[],"screenshots":[],"duration":47,"result":"SUCCESS"},{"number":30,"description":"Alice ensures that the text of flash message does include 'Your username is invalid!'","startTime":1666015658514,"children":[],"reportData":[],"screenshots":[{"screenshot":"photo-linux-chromium-106.0.5249.30-alice-ensures-that-the-text-of-flas-55b4a6be71.png","timeStamp":1666015658625}],"duration":11,"result":"SUCCESS"}],"reportData":[],"screenshots":[],"duration":180,"result":"SUCCESS"}],"reportData":[],"screenshots":[],"duration":330,"result":"SUCCESS"}],"reportData":[],"screenshots":[],"duration":2239,"result":"SUCCESS"}],"userStory":{"id":"form-based-authentication","storyName":"Form-Based Authentication","path":"features/authentication/form_authentication.feature","type":"feature","narrative":"In order to learn how to use Serenity/JS with Cucumber and WebdriverIO\nAs a Curious Developer\nI'd like to see an example"},"dataTable":{"scenarioOutline":"When she logs in using \"<username>\" and \"<password>\"\nThen she should see that authentication has <outcome>","dataSetDescriptors":[{"name":"","description":"","startRow":0,"rowCount":2}],"headers":["username","password","outcome"],"rows":[{"values":["tomsmith","SuperSecretPassword!","succeeded"],"result":"SUCCESS"},{"values":["foobar","barfoo","failed"],"result":"SUCCESS"}],"predefinedRows":true},"startTime":1666015653963,"testSource":"Cucumber","description":"[\"The Internet\"](https://the-internet.herokuapp.com/) is an example application\nthat captures prominent and ugly functionality found on the web.\nPerfect for writing automated acceptance tests against 😎\n\nNote: With **Serenity/JS** you can use [Markdown](https://en.wikipedia.org/wiki/Markdown)\nto better describe each `Feature` and `Scenario`.","tags":[{"name":"authentication","type":"capability","displayName":"authentication"},{"name":"authentication/Form-Based Authentication","type":"feature","displayName":"Form-Based Authentication"}],"featureTag":{"name":"authentication/Form-Based Authentication","type":"feature","displayName":"Form-Based Authentication"},"duration":4676}