{"id":"form-based-authentication;using-username-and-password-to-log-in","name":"Using username and password to log in","title":"Using username and password to log in","manual":false,"testSteps":[{"number":1,"description":"Using username and password to log in #1 - username: tomsmith, password: SuperSecretPassword!, outcome: succeeded","startTime":1704570127253,"children":[{"number":2,"description":"Given Alice starts with the \"Form Authentication\" example","startTime":1704570127256,"children":[{"number":3,"description":"Alice navigates to '/'","startTime":1704570127272,"children":[],"reportData":[],"screenshots":[{"screenshot":"photo-linux-chromium-120.0.6099.28-alice-navigates-to-b9b2f3eb22.png","timeStamp":1704570127904}],"duration":528,"result":"SUCCESS"},{"number":4,"description":"Alice picks example called Form Authentication","startTime":1704570127914,"children":[{"number":5,"description":"Alice clicks on the first of available examples where Text does equal 'Form Authentication'","startTime":1704570127914,"children":[],"reportData":[],"screenshots":[{"screenshot":"photo-linux-chromium-120.0.6099.28-alice-clicks-on-the-first-of-availa-661178fd1e.png","timeStamp":1704570128388}],"duration":381,"result":"SUCCESS"}],"reportData":[],"screenshots":[],"duration":481,"result":"SUCCESS"}],"reportData":[],"screenshots":[],"duration":1151,"result":"SUCCESS"},{"number":6,"description":"When she logs in using \"tomsmith\" and \"SuperSecretPassword!\"","startTime":1704570128407,"children":[{"number":7,"description":"Alice logs in as tomsmith","startTime":1704570128414,"children":[{"number":8,"description":"Alice enters 'tomsmith' into username field","startTime":1704570128414,"children":[],"reportData":[],"screenshots":[{"screenshot":"photo-linux-chromium-120.0.6099.28-alice-enters-tomsmith-into-userna-d6ec54d87b.png","timeStamp":1704570128521}],"duration":20,"result":"SUCCESS"},{"number":9,"description":"Alice enters 'SuperSecretPassword!' into password field","startTime":1704570128525,"children":[],"reportData":[],"screenshots":[{"screenshot":"photo-linux-chromium-120.0.6099.28-alice-enters-supersecretpassword-a30252b4f0.png","timeStamp":1704570128621}],"duration":13,"result":"SUCCESS"},{"number":10,"description":"Alice clicks on login button","startTime":1704570128629,"children":[],"reportData":[],"screenshots":[{"screenshot":"photo-linux-chromium-120.0.6099.28-alice-clicks-on-login-button-bbd1b2be5b.png","timeStamp":1704570128918}],"duration":163,"result":"SUCCESS"}],"reportData":[],"screenshots":[],"duration":508,"result":"SUCCESS"}],"reportData":[],"screenshots":[],"duration":525,"result":"SUCCESS"},{"number":11,"description":"Then she should see that authentication has succeeded","startTime":1704570128933,"children":[{"number":12,"description":"Alice verifies that authentication has succeeded","startTime":1704570128938,"children":[{"number":13,"description":"Alice verifies that flash alert is present","startTime":1704570128939,"children":[{"number":14,"description":"Alice ensures that flash message does become visible","startTime":1704570128939,"children":[],"reportData":[],"screenshots":[{"screenshot":"photo-linux-chromium-120.0.6099.28-alice-ensures-that-flash-message-do-f798d95d6d.png","timeStamp":1704570129068}],"duration":41,"result":"SUCCESS"}],"reportData":[],"screenshots":[],"duration":141,"result":"SUCCESS"},{"number":15,"description":"Alice ensures that the text of flash message does include 'You logged into a secure area!'","startTime":1704570129091,"children":[],"reportData":[],"screenshots":[{"screenshot":"photo-linux-chromium-120.0.6099.28-alice-ensures-that-the-text-of-flas-f798d95d6d.png","timeStamp":1704570129168}],"duration":3,"result":"SUCCESS"}],"reportData":[],"screenshots":[],"duration":236,"result":"SUCCESS"}],"reportData":[],"screenshots":[],"duration":252,"result":"SUCCESS"}],"reportData":[],"screenshots":[],"duration":1955,"result":"SUCCESS"},{"number":16,"description":"Using username and password to log in #2 - username: foobar, password: barfoo, outcome: failed","startTime":1704570129214,"children":[{"number":17,"description":"Given Alice starts with the \"Form Authentication\" example","startTime":1704570129215,"children":[{"number":18,"description":"Alice navigates to '/'","startTime":1704570129218,"children":[],"reportData":[],"screenshots":[{"screenshot":"photo-linux-chromium-120.0.6099.28-alice-navigates-to-b9b2f3eb22.png","timeStamp":1704570129653}],"duration":334,"result":"SUCCESS"},{"number":19,"description":"Alice picks example called Form Authentication","startTime":1704570129665,"children":[{"number":20,"description":"Alice clicks on the first of available examples where Text does equal 'Form Authentication'","startTime":1704570129665,"children":[],"reportData":[],"screenshots":[{"screenshot":"photo-linux-chromium-120.0.6099.28-alice-clicks-on-the-first-of-availa-661178fd1e.png","timeStamp":1704570130072}],"duration":319,"result":"SUCCESS"}],"reportData":[],"screenshots":[],"duration":411,"result":"SUCCESS"}],"reportData":[],"screenshots":[],"duration":870,"result":"SUCCESS"},{"number":21,"description":"When she logs in using \"foobar\" and \"barfoo\"","startTime":1704570130086,"children":[{"number":22,"description":"Alice logs in as foobar","startTime":1704570130090,"children":[{"number":23,"description":"Alice enters 'foobar' into username field","startTime":1704570130090,"children":[],"reportData":[],"screenshots":[{"screenshot":"photo-linux-chromium-120.0.6099.28-alice-enters-foobar-into-username-737313aded.png","timeStamp":1704570130188}],"duration":19,"result":"SUCCESS"},{"number":24,"description":"Alice enters 'barfoo' into password field","startTime":1704570130201,"children":[],"reportData":[],"screenshots":[{"screenshot":"photo-linux-chromium-120.0.6099.28-alice-enters-barfoo-into-password-2f5a79ca86.png","timeStamp":1704570130288}],"duration":10,"result":"SUCCESS"},{"number":25,"description":"Alice clicks on login button","startTime":1704570130292,"children":[],"reportData":[],"screenshots":[{"screenshot":"photo-linux-chromium-120.0.6099.28-alice-clicks-on-login-button-65aa9bec77.png","timeStamp":1704570130553}],"duration":152,"result":"SUCCESS"}],"reportData":[],"screenshots":[],"duration":467,"result":"SUCCESS"}],"reportData":[],"screenshots":[],"duration":482,"result":"SUCCESS"},{"number":26,"description":"Then she should see that authentication has failed","startTime":1704570130568,"children":[{"number":27,"description":"Alice verifies that authentication has failed","startTime":1704570130572,"children":[{"number":28,"description":"Alice verifies that flash alert is present","startTime":1704570130572,"children":[{"number":29,"description":"Alice ensures that flash message does become visible","startTime":1704570130572,"children":[],"reportData":[],"screenshots":[{"screenshot":"photo-linux-chromium-120.0.6099.28-alice-ensures-that-flash-message-do-21b9717c73.png","timeStamp":1704570130686}],"duration":31,"result":"SUCCESS"}],"reportData":[],"screenshots":[],"duration":121,"result":"SUCCESS"},{"number":30,"description":"Alice ensures that the text of flash message does include 'Your username is invalid!'","startTime":1704570130704,"children":[],"reportData":[],"screenshots":[{"screenshot":"photo-linux-chromium-120.0.6099.28-alice-ensures-that-the-text-of-flas-21b9717c73.png","timeStamp":1704570130786}],"duration":3,"result":"SUCCESS"}],"reportData":[],"screenshots":[],"duration":225,"result":"SUCCESS"}],"reportData":[],"screenshots":[],"duration":240,"result":"SUCCESS"}],"reportData":[],"screenshots":[],"duration":1616,"result":"SUCCESS"}],"userStory":{"id":"form-based-authentication","storyName":"Form-Based Authentication","path":"features/authentication/form_authentication.feature","type":"feature","narrative":"In order to learn how to use Serenity/JS with Cucumber and WebdriverIO\nAs a Curious Developer\nI'd like to see an example"},"dataTable":{"scenarioOutline":"When she logs in using \"<username>\" and \"<password>\"\nThen she should see that authentication has <outcome>","dataSetDescriptors":[{"name":"","description":"","startRow":0,"rowCount":2}],"headers":["username","password","outcome"],"rows":[{"values":["tomsmith","SuperSecretPassword!","succeeded"],"result":"SUCCESS"},{"values":["foobar","barfoo","failed"],"result":"SUCCESS"}],"predefinedRows":true},"startTime":1704570127253,"testSource":"Cucumber","description":"[\"The Internet\"](https://the-internet.herokuapp.com/) is an example application\nthat captures prominent and ugly functionality found on the web.\nPerfect for writing automated acceptance tests against 😎\n\nNote: With **Serenity/JS** you can use [Markdown](https://en.wikipedia.org/wiki/Markdown)\nto better describe each `Feature` and `Scenario`.","tags":[{"name":"Authentication","type":"capability","displayName":"Authentication"},{"name":"Authentication/Form-Based Authentication","type":"feature","displayName":"Form-Based Authentication"}],"featureTag":{"name":"Authentication/Form-Based Authentication","type":"feature","displayName":"Form-Based Authentication"},"duration":3577}